autokey/UI_common_functions.py
autokey/__init__.py
autokey/argument_parser.py
autokey/common.py
autokey/dbus_service.py
autokey/gtkapp.py
autokey/interface.py
autokey/logger.py
autokey/macro.py
autokey/monitor.py
autokey/qtapp.py
autokey/service.py
autokey/configmanager/__init__.py
autokey/configmanager/autostart.py
autokey/configmanager/configmanager.py
autokey/configmanager/configmanager_constants.py
autokey/configmanager/predefined_user_files.py
autokey/configmanager/version_upgrading.py
autokey/configmanager/predefined_user_scripts/_README.txt
autokey/configmanager/predefined_user_scripts/create_phrase_from_selection.pyi
autokey/configmanager/predefined_user_scripts/display_window_info.pyi
autokey/configmanager/predefined_user_scripts/insert_date.pyi
autokey/configmanager/predefined_user_scripts/list_menu.pyi
autokey/configmanager/predefined_user_scripts/new_abbreviation_from_selection.pyi
autokey/configmanager/predefined_user_scripts/selection_test.pyi
autokey/gtkui/__init__.py
autokey/gtkui/__main__.py
autokey/gtkui/configwindow.py
autokey/gtkui/dialogs.py
autokey/gtkui/notifier.py
autokey/gtkui/popupmenu.py
autokey/gtkui/settingsdialog.py
autokey/gtkui/shared.py
autokey/gtkui/data/abbrsettings.xml
autokey/gtkui/data/autokey.svg
autokey/gtkui/data/blankpage.xml
autokey/gtkui/data/detectdialog.xml
autokey/gtkui/data/folderpage.xml
autokey/gtkui/data/hotkeysettings.xml
autokey/gtkui/data/mainwindow.xml
autokey/gtkui/data/menus.xml
autokey/gtkui/data/phrasepage.xml
autokey/gtkui/data/recorddialog.xml
autokey/gtkui/data/renamedialog.xml
autokey/gtkui/data/scriptpage.xml
autokey/gtkui/data/settingsdialog.xml
autokey/gtkui/data/settingswidget.xml
autokey/gtkui/data/show_script_errors_dialog.xml
autokey/gtkui/data/windowfiltersettings.xml
autokey/iomediator/__init__.py
autokey/iomediator/constants.py
autokey/iomediator/iomediator.py
autokey/iomediator/keygrabber.py
autokey/iomediator/waiter.py
autokey/iomediator/windowgrabber.py
autokey/model/__init__.py
autokey-0.96.0.dist-info/LICENSE
autokey-0.96.0.dist-info/METADATA
autokey-0.96.0.dist-info/WHEEL
autokey-0.96.0.dist-info/entry_points.txt
autokey-0.96.0.dist-info/top_level.txt
autokey-0.96.0.dist-info/RECORD
