Metadata-Version: 2.1
Name: autokey
Version: 0.96.0
Summary: Keyboard and GUI automation on Linux (X11)
Home-page: https://github.com/autokey/autokey
Author: Chris Dekter
Author-email: cdekter@gmail.com
Maintainer: GuoCi
Maintainer-email: guociz@gmail.com
License: GPLv3
Keywords: automation hotkey expansion expander phrase
Classifier: Development Status :: 4 - Beta
Classifier: Intended Audience :: Developers
Classifier: Intended Audience :: End Users/Desktop
Classifier: License :: OSI Approved :: GNU General Public License v3 (GPLv3)
Classifier: Natural Language :: English
Classifier: Operating System :: POSIX :: Linux
Classifier: Programming Language :: Python :: 3.5
Requires-Python: >=3.5
License-File: LICENSE
Requires-Dist: pyinotify
Requires-Dist: python-xlib
Requires-Dist: packaging
